imgdude/__init__.py
imgdude/_version.py
imgdude/cache.py
imgdude/cli.py
imgdude/main.py
imgdude-1.0.1.dist-info/licenses/LICENSE
imgdude-1.0.1.dist-info/METADATA
imgdude-1.0.1.dist-info/WHEEL
imgdude-1.0.1.dist-info/entry_points.txt
imgdude-1.0.1.dist-info/top_level.txt
imgdude-1.0.1.dist-info/RECORD
