Metadata-Version: 2.4
Name: imgdude
Version: 1.0.1
Summary: Fast image resizing proxy standalone backend with FastAPI
Author-email: ASafarzadeh <includesafarof@gmail.com>
License: MIT
Project-URL: Homepage, https://github.com/ASafarzadeh/imgdude
Project-URL: Documentation, https://github.com/ASafarzadeh/imgdude#readme
Project-URL: Bug Tracker, https://github.com/ASafarzadeh/imgdude/issues
Project-URL: Source, https://github.com/ASafarzadeh/imgdude
Classifier: Development Status :: 4 - Beta
Classifier: Intended Audience :: Developers
Classifier: License :: OSI Approved :: MIT License
Classifier: Programming Language :: Python :: 3
Classifier: Programming Language :: Python :: 3.8
Classifier: Programming Language :: Python :: 3.9
Classifier: Programming Language :: Python :: 3.10
Classifier: Programming Language :: Python :: 3.11
Classifier: Programming Language :: Python :: 3.12
Classifier: Topic :: Internet :: WWW/HTTP
Classifier: Topic :: Multimedia :: Graphics
Requires-Python: >=3.8
License-File: LICENSE
Requires-Dist: fastapi>=0.100.0
Requires-Dist: pillow>=9.0.0
Requires-Dist: uvicorn[standard]>=0.23.0
Requires-Dist: aiofiles>=23.0.0
Requires-Dist: python-multipart>=0.0.5
Provides-Extra: dev
Requires-Dist: pytest>=7.0.0; extra == "dev"
Requires-Dist: pytest-asyncio>=0.21.0; extra == "dev"
Requires-Dist: pytest-cov>=4.0.0; extra == "dev"
Requires-Dist: black>=23.0.0; extra == "dev"
Requires-Dist: flake8>=6.0.0; extra == "dev"
Requires-Dist: mypy>=1.0.0; extra == "dev"
Requires-Dist: httpx>=0.24.0; extra == "dev"
Dynamic: license-file
